girder_jsonforms/__init__.py
girder_jsonforms/settings.py
girder_jsonforms/lib/__init__.py
girder_jsonforms/lib/google_drive.py
girder_jsonforms/lib/jq.py
girder_jsonforms/models/__init__.py
girder_jsonforms/models/entry.py
girder_jsonforms/models/form.py
girder_jsonforms/rest/__init__.py
girder_jsonforms/rest/entry.py
girder_jsonforms/rest/form.py
girder_jsonforms/web_client/dist/girder-plugin-jsonforms.umd.cjs
girder_jsonforms/web_client/dist/style.css
girder_jsonforms-2.0.7.dist-info/licenses/LICENSE
girder_jsonforms-2.0.7.dist-info/METADATA
girder_jsonforms-2.0.7.dist-info/WHEEL
girder_jsonforms-2.0.7.dist-info/entry_points.txt
girder_jsonforms-2.0.7.dist-info/top_level.txt
girder_jsonforms-2.0.7.dist-info/RECORD
