Metadata-Version: 2.4
Name: girder-jsonforms
Version: 2.0.7
Summary: Girder plugin adding forms based on JSON-editor
License: BSD-3-Clause
Classifier: Development Status :: 4 - Beta
Classifier: Environment :: Web Environment
Classifier: License :: OSI Approved :: BSD License
Classifier: Operating System :: POSIX :: Linux
Classifier: Programming Language :: Python
Classifier: Programming Language :: Python :: 3
Requires-Python: >=3.10
License-File: LICENSE
Requires-Dist: girder>=5.0.0a5.dev0
Requires-Dist: google-api-python-client
Requires-Dist: google-auth-oauthlib
Requires-Dist: pandas
Dynamic: classifier
Dynamic: description
Dynamic: description-content-type
Dynamic: license
Dynamic: license-file
Dynamic: requires-dist
Dynamic: requires-python
Dynamic: summary
